unitypredict_engines/Models.py
unitypredict_engines/Platform.py
unitypredict_engines/UnityPredictLocalHost.py
unitypredict_engines/__init__.py
unitypredict_engines/scripts.py
unitypredict_engines/unitypredictUtils.py
unitypredict_engines/unitypredictcli.py
unitypredict_engines-1.1.80.dist-info/METADATA
unitypredict_engines-1.1.80.dist-info/WHEEL
unitypredict_engines-1.1.80.dist-info/entry_points.txt
unitypredict_engines-1.1.80.dist-info/top_level.txt
unitypredict_engines-1.1.80.dist-info/RECORD
